nonebot_plugin_javamc_status/__init__.py
nonebot_plugin_javamc_status-0.1.3.dist-info/METADATA
nonebot_plugin_javamc_status-0.1.3.dist-info/WHEEL
nonebot_plugin_javamc_status-0.1.3.dist-info/RECORD
