Metadata-Version: 2.1
Name: nonebot-plugin-javamc-status
Version: 0.1.3
Summary: Nonebot2查询JAVA MC服务器在线信息插件
Home-page: https://github.com/nikissXI/nonebot_plugins/tree/main/nonebot_plugin_javamc_status
License: MIT
Author: nikissXI
Author-email: 1299577815@qq.com
Requires-Python: >=3.9,<4.0
Classifier: License :: OSI Approved :: MIT License
Classifier: Programming Language :: Python :: 3
Classifier: Programming Language :: Python :: 3.9
Classifier: Programming Language :: Python :: 3.10
Classifier: Programming Language :: Python :: 3.11
Requires-Dist: nonebot-adapter-onebot (>=2.0.0,<3.0.0)
Requires-Dist: nonebot2 (>=2.0.0-rc.1,<3.0.0)
Project-URL: Documentation, https://github.com/nikissXI/nonebot_plugins/tree/main/nonebot_plugin_javamc_status#README.md
Project-URL: Repository, https://github.com/nikissXI/nonebot_plugins/tree/main/nonebot_plugin_javamc_status
